udl_vis/__init__.py
udl_vis/AutoDL/__init__.py
udl_vis/AutoDL/base_runner.py
udl_vis/AutoDL/trainer.py
udl_vis/Basis/__init__.py
udl_vis/Basis/cal_ssim.py
udl_vis/Basis/config.py
udl_vis/Basis/criterion_metrics.py
udl_vis/Basis/dist_utils.py
udl_vis/Basis/launch.py
udl_vis/Basis/logger.py
udl_vis/Basis/metrics.py
udl_vis/Basis/module.py
udl_vis/Basis/optim.py
udl_vis/Basis/option.py
udl_vis/Basis/postprocess.py
udl_vis/Basis/python_sub_class.py
udl_vis/Basis/variance_sacling_initializer.py
udl_vis/Basis/auxiliary/__init__.py
udl_vis/Basis/auxiliary/base.py
udl_vis/Basis/auxiliary/fp16_utils.py
udl_vis/Basis/auxiliary/utils.py
udl_vis/Basis/auxiliary/torchstat/__init__.py
udl_vis/Basis/auxiliary/torchstat/__main__.py
udl_vis/Basis/auxiliary/torchstat/compute_flops.py
udl_vis/Basis/auxiliary/torchstat/compute_madd.py
udl_vis/Basis/auxiliary/torchstat/compute_memory.py
udl_vis/Basis/auxiliary/torchstat/model_hook.py
udl_vis/Basis/auxiliary/torchstat/reporter.py
udl_vis/Basis/auxiliary/torchstat/stat_tree.py
udl_vis/Basis/auxiliary/torchstat/statistics.py
udl_vis/mmcv/__init__.py
udl_vis/mmcv/version.py
udl_vis/mmcv/arraymisc/__init__.py
udl_vis/mmcv/arraymisc/quantization.py
udl_vis/mmcv/cnn/__init__.py
udl_vis/mmcv/cnn/alexnet.py
udl_vis/mmcv/cnn/builder.py
udl_vis/mmcv/cnn/resnet.py
udl_vis/mmcv/cnn/vgg.py
udl_vis/mmcv/cnn/bricks/__init__.py
udl_vis/mmcv/cnn/bricks/activation.py
udl_vis/mmcv/cnn/bricks/context_block.py
udl_vis/mmcv/cnn/bricks/conv.py
udl_vis/mmcv/cnn/bricks/conv2d_adaptive_padding.py
udl_vis/mmcv/cnn/bricks/conv_module.py
udl_vis/mmcv/cnn/bricks/conv_ws.py
udl_vis/mmcv/cnn/bricks/depthwise_separable_conv_module.py
udl_vis/mmcv/cnn/bricks/drop.py
udl_vis/mmcv/cnn/bricks/generalized_attention.py
udl_vis/mmcv/cnn/bricks/hsigmoid.py
udl_vis/mmcv/cnn/bricks/hswish.py
udl_vis/mmcv/cnn/bricks/non_local.py
udl_vis/mmcv/cnn/bricks/norm.py
udl_vis/mmcv/cnn/bricks/padding.py
udl_vis/mmcv/cnn/bricks/plugin.py
udl_vis/mmcv/cnn/bricks/registry.py
udl_vis-0.3.7.dist-info/LICENSE
udl_vis-0.3.7.dist-info/METADATA
udl_vis-0.3.7.dist-info/WHEEL
udl_vis-0.3.7.dist-info/top_level.txt
udl_vis-0.3.7.dist-info/RECORD
